micropython_lis3mdl/__init__.py
micropython_lis3mdl/i2c_helpers.py
micropython_lis3mdl/lis3mdl.py
micropython_lis3mdl-0.2.0.dist-info/LICENSE
micropython_lis3mdl-0.2.0.dist-info/METADATA
micropython_lis3mdl-0.2.0.dist-info/WHEEL
micropython_lis3mdl-0.2.0.dist-info/top_level.txt
micropython_lis3mdl-0.2.0.dist-info/RECORD
