Metadata-Version: 2.1
Name: micropython-lis3mdl
Version: 0.2.0
Summary: MicroPython Driver for the ST LIS3MDL magnetometer
Author-email: JDM <xxyx@mailmeto.mozmail.com>
License: MIT
Project-URL: Homepage, https://github.com/jposada202020/MicroPython_LIS3MDL
Keywords: sensor,micropython,lis3mdl,magnetometer,temperature,driver
Classifier: Intended Audience :: Developers
Classifier: Topic :: Software Development :: Libraries
Classifier: Topic :: Software Development :: Embedded Systems
Classifier: Topic :: System :: Hardware
Classifier: License :: OSI Approved :: MIT License
Classifier: Programming Language :: Python :: Implementation :: MicroPython
License-File: LICENSE
